<PAMDataset>
  <PAMRasterBand band="1">
    <Histograms>
      <HistItem>
        <HistMin>-0.699999988079071</HistMin>
        <HistMax>4.025000095367432</HistMax>
        <BucketCount>256</BucketCount>
        <IncludeOutOfRange>1</IncludeOutOfRange>
        <Approximate>0</Approximate>
        <HistCounts>2|0|1|2|3|2|6|21|19|11|5|14|10|9|20|15|19|14|18|22|25|23|34|46|31|45|55|47|62|77|129|129|256|321|788|1879|3389|295255|11460|4126|2733|2189|1869|1333|895|752|568|393|342|315|243|205|210|154|156|154|141|117|131|98|96|86|92|80|80|105|94|66|66|75|69|72|69|50|45|44|41|41|39|31|35|39|41|38|34|35|32|36|205|35|46|32|36|36|36|45|17|27|46|30|45|30|32|41|32|7|10|10|11|10|6|9|9|9|9|11|6|12|2|7|5|8|9|7|7|5|8|4|8|7|17|6|16|14|8|5|1|7|4|3|4|5|3|7|4|8|4|8|1|3|10|11|2|13|9|26|31|48|30|160|234|164|3|24|3|2|3|3|0|2|2|1|0|3|2|6|2|0|0|2|0|0|3|1|2|1|0|1|0|0|0|1|1|0|0|1|0|0|1|0|1|0|0|0|0|0|0|0|0|0|0|0|0|0|0|0|0|1|0|0|0|0|0|0|1|0|0|0|0|0|0|0|0|0|0|0|0|0|0|0|0|0|0|0|0|0|0|0|0|0|0|0|0|0|0|1</HistCounts>
      </HistItem>
    </Histograms>
    <Metadata>
      <MDI key="STATISTICS_COVARIANCES">0.02057479387078688</MDI>
      <MDI key="STATISTICS_EXCLUDEDVALUES"></MDI>
      <MDI key="STATISTICS_MAXIMUM">4.0250000953674</MDI>
      <MDI key="STATISTICS_MEAN">0.016561771780474</MDI>
      <MDI key="STATISTICS_MINIMUM">-0.69999998807907</MDI>
      <MDI key="STATISTICS_SKIPFACTORX">1</MDI>
      <MDI key="STATISTICS_SKIPFACTORY">1</MDI>
      <MDI key="STATISTICS_STDDEV">0.14343916435474</MDI>
    </Metadata>
  </PAMRasterBand>
</PAMDataset>
